pytermstructure/__init__.py
pytermstructure/analysis.py
pytermstructure/core.py
pytermstructure/help_system.py
pytermstructure/helpers.py
pytermstructure/methods.py
pytermstructure-0.1.0.dist-info/licenses/LICENSE
pytermstructure-0.1.0.dist-info/METADATA
pytermstructure-0.1.0.dist-info/WHEEL
pytermstructure-0.1.0.dist-info/top_level.txt
pytermstructure-0.1.0.dist-info/RECORD
