Metadata-Version: 2.4
Name: pytermstructure
Version: 0.1.0
Summary: Educational Python library for interest rate term structure estimation
Home-page: https://github.com/MarcoGigante/pytermstructure
Author: Marco Gigante
License: GPL-3.0-or-later
Project-URL: Homepage, https://github.com/MarcoGigante/pytermstructure
Project-URL: Repository, https://github.com/MarcoGigante/pytermstructure
Project-URL: Issues, https://github.com/MarcoGigante/pytermstructure/issues
Project-URL: Documentation, https://pytermstructure.readthedocs.io
Project-URL: Changelog, https://github.com/MarcoGigante/pytermstructure/blob/main/CHANGELOG.md
Keywords: finance,interest-rates,term-structure,yield-curve,quantitative-finance
Classifier: Development Status :: 4 - Beta
Classifier: Intended Audience :: Education
Classifier: Intended Audience :: Science/Research
Classifier: Intended Audience :: Financial and Insurance Industry
Classifier: License :: OSI Approved :: GNU General Public License v3 (GPLv3)
Classifier: Programming Language :: Python :: 3
Classifier: Programming Language :: Python :: 3.8
Classifier: Programming Language :: Python :: 3.9
Classifier: Programming Language :: Python :: 3.10
Classifier: Programming Language :: Python :: 3.11
Classifier: Programming Language :: Python :: 3.12
Classifier: Topic :: Office/Business :: Financial
Classifier: Topic :: Scientific/Engineering :: Mathematics
Requires-Python: >=3.8
License-File: LICENSE
Requires-Dist: numpy>=1.20.0
Requires-Dist: scipy>=1.7.0
Requires-Dist: python-dateutil>=2.8.0
Provides-Extra: dev
Requires-Dist: pytest>=7.0; extra == "dev"
Requires-Dist: pytest-cov>=3.0; extra == "dev"
Requires-Dist: black>=22.0; extra == "dev"
Requires-Dist: flake8>=4.0; extra == "dev"
Provides-Extra: docs
Requires-Dist: sphinx>=4.0; extra == "docs"
Requires-Dist: sphinx-rtd-theme>=1.0; extra == "docs"
Dynamic: home-page
Dynamic: license-file
Dynamic: requires-python
